{
    "id": 5692646,
    "title": "Harvest + Greg Laurie on Lightsource.com - Audio",
    "url": "https://www.lightsource.com/ministry/greg-laurie-tv/subscribe/podcast-audio.xml",
    "originalUrl": "https://www.lightsource.com/ministry/greg-laurie-tv/subscribe/podcast-audio.xml",
    "lastUpdateTime": 0,
    "lastCrawlTime": 0,
    "lastParseTime": 0,
    "lastGoodHttpStatusTime": 0,
    "lastHttpStatus": 200,
    "itunesId": 1626535221,
    "dead": 0,
    "episodeCount": 0,
    "crawlErrors": 0,
    "parseErrors": 0,
    "locked": 0,
    "ownerId": null,
    "pendingUpdate": 0,
    "pullNow": 0,
    "hasVideo": false,
    "hasRealtimeUpdates": false,
    "hasSubscribers": false,
    "itemUrlStrings": "",
    "itunesNewFeedUrl": null,
    "lastBuildDate": null
}